ex_dataclass/__init__.py
ex_dataclass/__prototype.py
ex_dataclass/core.py
ex_dataclass/error.py
ex_dataclass/ex_dataclass.py
ex_dataclass/ex_field.py
ex_dataclass/m.py
ex_dataclass/type_.py
ex_dataclass/xpack.py
ex_dataclass-1.2.0.dist-info/LICENSE
ex_dataclass-1.2.0.dist-info/METADATA
ex_dataclass-1.2.0.dist-info/WHEEL
ex_dataclass-1.2.0.dist-info/top_level.txt
ex_dataclass-1.2.0.dist-info/RECORD
