Metadata-Version: 2.1
Name: ex-dataclass
Version: 1.2.0
Summary: A more powerful data model management than DataClass that reduces maintenance costs and improves coding efficiency.
Home-page: https://github.com/Shadow-linux/ex_dataclass
Author: ShadowYD
Author-email: 972367265@qq.com
License: UNKNOWN
Platform: UNKNOWN
Requires-Python: >=3.7
License-File: LICENSE
